my_programs/__init__.py
my_programs/program1.py
my_programs/program10.py
my_programs/program11.py
my_programs/program12.py
my_programs/program13.py
my_programs/program2.py
my_programs/program3.py
my_programs/program4.py
my_programs/program5.py
my_programs/program6.py
my_programs/program7.py
my_programs/program8.py
my_programs/program9.py
my_programs/__pycache__/__init__.cpython-310.pyc
my_programs/__pycache__/program1.cpython-310.pyc
my_programs/__pycache__/program10.cpython-310.pyc
my_programs/__pycache__/program11.cpython-310.pyc
my_programs/__pycache__/program2.cpython-310.pyc
my_programs/__pycache__/program3.cpython-310.pyc
my_programs/__pycache__/program4.cpython-310.pyc
my_programs/__pycache__/program5.cpython-310.pyc
my_programs/__pycache__/program6.cpython-310.pyc
my_programs/__pycache__/program7.cpython-310.pyc
my_programs/__pycache__/program8.cpython-310.pyc
my_programs/__pycache__/program9.cpython-310.pyc
math_test_programs-1.2.dist-info/METADATA
math_test_programs-1.2.dist-info/WHEEL
math_test_programs-1.2.dist-info/top_level.txt
math_test_programs-1.2.dist-info/RECORD
