Metadata-Version: 2.2
Name: math_test_programs
Version: 1.2
Summary: A collection of 13 Python programs for math-related tasks
Home-page: https://github.com/yourusername/math-test-programs
Author: Sachethan
Classifier: Programming Language :: Python :: 3
Classifier: License :: OSI Approved :: MIT License
Classifier: Operating System :: OS Independent
Requires-Python: >=3.6
Dynamic: author
Dynamic: classifier
Dynamic: description
Dynamic: description-content-type
Dynamic: home-page
Dynamic: requires-python
Dynamic: summary
